{
  "meta": {
    "id": "tvmaze:77794",
    "type": "series",
    "name": "Haha, You Clowns",
    "description": "Haha You Clowns follows three sweet natured brothers who, alongside their deeply caring father, embark on various adventures as they bond together in the wake of their mother's passing.",
    "poster": "https://static.tvmaze.com/uploads/images/original_untouched/593/1484188.jpg",
    "background": "https://static.tvmaze.com/uploads/images/original_untouched/593/1484188.jpg",
    "videos": [
      {
        "id": "tvmaze:3451819",
        "title": "Therapy",
        "season": 1,
        "episode": 9,
        "released": "2025-12-14",
        "overview": "The boys get a cool new therapist."
      },
      {
        "id": "tvmaze:3457165",
        "title": "Improv",
        "season": 1,
        "episode": 10,
        "released": "2025-12-21",
        "overview": "Tristan gets immersed in a new hobby."
      },
      {
        "id": "tvmaze:3449562",
        "title": "Call to the Battalion",
        "season": 1,
        "episode": 8,
        "released": "2025-12-07",
        "overview": "The boys try to set Dad up on a date to find love."
      },
      {
        "id": "tvmaze:3397572",
        "title": "Movie Night",
        "season": 1,
        "episode": 1,
        "released": "2025-10-19",
        "overview": "The boys try to figure out why Dad can't stay awake during movie night."
      },
      {
        "id": "tvmaze:3397573",
        "title": "Viral",
        "season": 1,
        "episode": 2,
        "released": "2025-10-26",
        "overview": "The boys convince Dad to try and go viral during his weather report."
      },
      {
        "id": "tvmaze:3397574",
        "title": "Bomber Jacket",
        "season": 1,
        "episode": 3,
        "released": "2025-11-02",
        "overview": "Preston loses his beloved World War II bomber jacket."
      },
      {
        "id": "tvmaze:3423769",
        "title": "Plane",
        "season": 1,
        "episode": 4,
        "released": "2025-11-09",
        "overview": "Dad confronts his fear of flying on the way to Mexico."
      },
      {
        "id": "tvmaze:3426520",
        "title": "Duncan Holds a Baby",
        "season": 1,
        "episode": 5,
        "released": "2025-11-16",
        "overview": "Duncan struggles to hide his fear of holding babies."
      },
      {
        "id": "tvmaze:3436530",
        "title": "Dad's Birthday",
        "season": 1,
        "episode": 6,
        "released": "2025-11-23",
        "overview": "Dad's old friends are in town for his birthday, and they have quite the stories to tell."
      },
      {
        "id": "tvmaze:3443691",
        "title": "Hot Tub",
        "season": 1,
        "episode": 7,
        "released": "2025-11-30",
        "overview": "The boys beg Dad to let them get a hot tub."
      }
    ]
  }
}